pick2/__init__.py
pick2-0.7.1.dist-info/DESCRIPTION.rst
pick2-0.7.1.dist-info/METADATA
pick2-0.7.1.dist-info/RECORD
pick2-0.7.1.dist-info/WHEEL
pick2-0.7.1.dist-info/metadata.json
pick2-0.7.1.dist-info/top_level.txt
