Metadata-Version: 2.0
Name: pick2
Version: 0.7.1
Summary: pick an option in the terminal with a simple GUI
Home-page: https://github.com/wong2/pick
Author: jaitaiwan
Author-email: dan@djcentric.com
License: MIT
Keywords: terminal gui
Platform: UNKNOWN
Classifier: Intended Audience :: Developers
Classifier: License :: OSI Approved :: MIT License
Classifier: Programming Language :: Python
Classifier: Programming Language :: Python :: 3.6
